silicondiff_comfy_nodes/_nodes.py
silicondiff_comfy_nodes/__init__.py
silicondiff_comfy_nodes/_config.py
silicondiff_comfy_nodes/prestartup_script.py
silicondiff_comfy_nodes/modules/sd_hijack_utils.py
silicondiff_comfy_nodes/modules/booster_interface.py
silicondiff_comfy_nodes/modules/booster_scheduler.py
silicondiff_comfy_nodes/modules/__init__.py
silicondiff_comfy_nodes/modules/booster_cache.py
silicondiff_comfy_nodes/modules/silicondiff_compile/hijack_samplers.py
silicondiff_comfy_nodes/modules/silicondiff_compile/booster_utils.py
silicondiff_comfy_nodes/modules/silicondiff_compile/hijack_model_patcher.py
silicondiff_comfy_nodes/modules/silicondiff_compile/silicondiff_controlnet.py
silicondiff_comfy_nodes/modules/silicondiff_compile/__init__.py
silicondiff_comfy_nodes/modules/silicondiff_compile/booster_basic.py
silicondiff_comfy_nodes/modules/silicondiff_compile/patch_management/__init__.py
silicondiff_comfy_nodes/modules/silicondiff_compile/patch_management/patch_factory.py
silicondiff_comfy_nodes/modules/silicondiff_compile/patch_management/patch_executor.py
silicondiff_comfy_nodes/modules/silicondiff_compile/hijack_pulid_comfyui/pulid.py
silicondiff_comfy_nodes/modules/silicondiff_compile/hijack_pulid_comfyui/__init__.py
silicondiff_comfy_nodes/modules/silicondiff_compile/hijack_pulid_comfyui/_config.py
silicondiff_comfy_nodes/modules/silicondiff_compile/hijack_ipadapter_plus/set_model_patch_replace.py
silicondiff_comfy_nodes/modules/silicondiff_compile/hijack_ipadapter_plus/CrossAttentionPatch.py
silicondiff_comfy_nodes/modules/silicondiff_compile/hijack_ipadapter_plus/__init__.py
silicondiff_comfy_nodes/modules/silicondiff_compile/hijack_ipadapter_plus/IPAdapterPlus.py
silicondiff_comfy_nodes/modules/silicondiff_compile/hijack_ipadapter_plus/_config.py
silicondiff_comfy_nodes/modules/silicondiff_compile/hijack_comfyui_instantid/InstantID.py
silicondiff_comfy_nodes/modules/silicondiff_compile/hijack_comfyui_instantid/__init__.py
silicondiff_npu-2.3.1.post3.dist-info/RECORD
silicondiff_npu-2.3.1.post3.dist-info/METADATA
silicondiff_npu-2.3.1.post3.dist-info/WHEEL
silicondiff_npu-2.3.1.post3.dist-info/top_level.txt
