Metadata-Version: 2.1
Name: silicondiff_npu
Version: 2.3.1.post3
Summary: SiliconDiff-NPU
Requires-Dist: pyyaml
Requires-Dist: cmake
Requires-Dist: pybind11
Requires-Dist: setuptools
Requires-Dist: setuptools-scm
Requires-Dist: loguru
Requires-Dist: torch
Requires-Dist: torch-npu
Requires-Dist: diffusers
